AUTHORS.md
ChangeLog.txt
LICENSE.txt
MANAGEMENT.md
MANIFEST.in
README.rst
requirements.txt
setup.py
SPARQLWrapper/KeyCaseInsensitiveDict.py
SPARQLWrapper/SPARQLExceptions.py
SPARQLWrapper/SmartWrapper.py
SPARQLWrapper/Wrapper.py
SPARQLWrapper/__init__.py
SPARQLWrapperMosorio.egg-info/PKG-INFO
SPARQLWrapperMosorio.egg-info/SOURCES.txt
SPARQLWrapperMosorio.egg-info/dependency_links.txt
SPARQLWrapperMosorio.egg-info/requires.txt
SPARQLWrapperMosorio.egg-info/top_level.txt
custom_fixers/__init__.py
custom_fixers/fix_urllib2.py
custom_fixers/__pycache__/__init__.cpython-37.pyc
custom_fixers/__pycache__/fix_urllib2.cpython-37.pyc
scripts/example-ask.py
scripts/example-construct.py
scripts/example-dbpedia.py
scripts/example-delete.py
scripts/example-describe.py
scripts/example-federated.py
scripts/example-insert-using-rdflib.py
scripts/example-insert.py
scripts/example-optional.py
scripts/example.py
scripts/sparql.py
test/4store__v1_1_5__agroportal__test.py
test/agrovoc-allegrograph_on_hold.py
test/allegrograph__v4_14_1__mmi__test.py
test/blazegraph__wikidata__test.py
test/fuseki2__v3_6_0__agrovoc__test.py
test/fuseki2__v3_8_0__stw__test.py
test/graphdbEnterprise__v8_9_0__rs__test.py
test/lov-fuseki_on_hold.py
test/rdf4j__geosciml__test.py
test/stardog__lindas__test.py
test/virtuoso__v7_20_3230__dbpedia__test.py
test/virtuoso__v8_03_3313__dbpedia__test.py
test/wrapper_test.py