Metadata-Version: 2.1
Name: SPARQLWrapperMosorio
Version: 1.8.6
Summary: SPARQL Endpoint interface to Python
Home-page: http://rdflib.github.io/sparqlwrapper
Author: Ivan Herman, Sergio Fernández, Carlos Tejo Alonso, Alexey Zakhlestin
License: W3C SOFTWARE NOTICE AND LICENSE
Download-URL: https://github.com/RDFLib/sparqlwrapper/releases
Project-URL: Home, https://rdflib.github.io/sparqlwrapper/
Project-URL: Documentation, https://rdflib.github.io/sparqlwrapper/doc/
Project-URL: Source, https://github.com/RDFLib/sparqlwrapper
Project-URL: Tracker, https://github.com/RDFLib/sparqlwrapper/issues
Keywords: python,sparql,rdf,rdflib
Platform: any
Classifier: Development Status :: 5 - Production/Stable
Classifier: Intended Audience :: Developers
Classifier: License :: OSI Approved :: W3C License
Classifier: Operating System :: OS Independent
Classifier: Programming Language :: Python :: 2
Classifier: Programming Language :: Python :: 2.7
Classifier: Programming Language :: Python :: 3
Classifier: Programming Language :: Python :: 3.3
Classifier: Programming Language :: Python :: 3.4
Classifier: Programming Language :: Python :: 3.5
Classifier: Programming Language :: Python :: 3.6
Classifier: Programming Language :: Python :: 3.7
Classifier: Programming Language :: Python :: Implementation :: CPython
Classifier: Programming Language :: Python :: Implementation :: PyPy
Classifier: Topic :: Software Development :: Libraries :: Python Modules
Provides-Extra: keepalive
